[
  {
    "id": "e6fe7254-1271-4dab-8c6c-56c85118dfa2",
    "title": "katy perry fire work will jake 1st bounce 9925.wav",
    "fileName": "e6fe7254-1271-4dab-8c6c-56c85118dfa2.wav",
    "type": "audio",
    "sizeBytes": 36931452,
    "createdAt": "2025-11-23T21:55:18.730Z",
    "protected": false
  },
  {
    "id": "47cb54c7-1f0b-4f57-8151-3b660dc6d1de",
    "title": "_piece of my heart AB 12425 192 32 not nrmlzd -14lufs w buster se.wav",
    "fileName": "47cb54c7-1f0b-4f57-8151-3b660dc6d1de.wav",
    "type": "audio",
    "sizeBytes": 885673268,
    "createdAt": "2025-11-24T21:58:21.328Z",
    "protected": false
  },
  {
    "id": "9c2600db-3a2b-498e-8f49-4ee874f88f03",
    "title": "backseat jane 1st bounce 1_24_25 192 32 nrmlzd 2.wav",
    "fileName": "9c2600db-3a2b-498e-8f49-4ee874f88f03.wav",
    "type": "audio",
    "sizeBytes": 748220340,
    "createdAt": "2025-11-24T22:04:38.417Z",
    "protected": false
  },
  {
    "id": "924f3819-15c3-40e2-8b0f-291bf6ca70c4",
    "title": "say syaonara w dex.wav",
    "fileName": "924f3819-15c3-40e2-8b0f-291bf6ca70c4.wav",
    "type": "audio",
    "sizeBytes": 90001408,
    "createdAt": "2025-11-24T22:09:23.107Z",
    "protected": false
  },
  {
    "id": "30aa25c5-6f6e-4668-911a-00947ddc6d7a",
    "title": "piano 1st versionthe moon hangs low in the denver sky 192 32 nrmlzd.wav",
    "fileName": "30aa25c5-6f6e-4668-911a-00947ddc6d7a.wav",
    "type": "audio",
    "sizeBytes": 743424044,
    "createdAt": "2025-11-25T00:08:44.543Z",
    "protected": false
  },
  {
    "id": "c1df3053-2ad4-4e69-a933-3a5d942da029",
    "title": "piano 1st versionthe moon hangs low in the denver sky 192 32 nrmlzd.wav",
    "fileName": "c1df3053-2ad4-4e69-a933-3a5d942da029.wav",
    "type": "audio",
    "sizeBytes": 743424044,
    "createdAt": "2025-11-25T02:18:28.886Z",
    "protected": false
  },
  {
    "id": "a2ca7090-db5e-412e-9f6c-68fa4e4ca650",
    "title": "say syaonara w dex.wav",
    "fileName": "a2ca7090-db5e-412e-9f6c-68fa4e4ca650.wav",
    "type": "audio",
    "sizeBytes": 90001408,
    "createdAt": "2025-11-25T03:34:28.699Z",
    "protected": false
  },
  {
    "id": "cfe215cd-575e-4c22-b4b3-a474d12f0dd2",
    "title": "piano 1st versionthe moon hangs low in the denver sky 192 32 nrmlzd.wav",
    "fileName": "cfe215cd-575e-4c22-b4b3-a474d12f0dd2.wav",
    "type": "audio",
    "sizeBytes": 743424044,
    "createdAt": "2025-11-25T03:34:31.416Z",
    "protected": false
  },
  {
    "id": "11b51d93-0042-414e-a478-dcbe25e4d4e9",
    "title": "backseat jane 1st bounce 1:24:25 192 32 not nrmlzd.wav",
    "fileName": "11b51d93-0042-414e-a478-dcbe25e4d4e9.wav",
    "type": "audio",
    "sizeBytes": 748220340,
    "createdAt": "2025-11-25T10:06:18.460Z",
    "protected": false
  }
]